gaitmap_datasets/__init__.py
gaitmap_datasets/_config.py
gaitmap_datasets/egait_adidas_2014/__init__.py
gaitmap_datasets/egait_adidas_2014/_dataset.py
gaitmap_datasets/egait_adidas_2014/helper.py
gaitmap_datasets/egait_parameter_validation_2013/__init__.py
gaitmap_datasets/egait_parameter_validation_2013/_dataset.py
gaitmap_datasets/egait_parameter_validation_2013/helper.py
gaitmap_datasets/egait_segmentation_validation_2014/__init__.py
gaitmap_datasets/egait_segmentation_validation_2014/_dataset.py
gaitmap_datasets/egait_segmentation_validation_2014/helper.py
gaitmap_datasets/kluge_2017/__init__.py
gaitmap_datasets/kluge_2017/_dataset.py
gaitmap_datasets/kluge_2017/helper.py
gaitmap_datasets/pyshoe_2019/__init__.py
gaitmap_datasets/pyshoe_2019/_dataset.py
gaitmap_datasets/pyshoe_2019/helper.py
gaitmap_datasets/sensor_position_comparison_2019/__init__.py
gaitmap_datasets/sensor_position_comparison_2019/_dataset.py
gaitmap_datasets/sensor_position_comparison_2019/helper.py
gaitmap_datasets/stair_ambulation_healthy_2021/__init__.py
gaitmap_datasets/stair_ambulation_healthy_2021/_dataset.py
gaitmap_datasets/stair_ambulation_healthy_2021/helper.py
gaitmap_datasets/stair_ambulation_healthy_2021/pressure_sensor_helper.py
gaitmap_datasets/stair_ambulation_healthy_2021/scripts/__init__.py
gaitmap_datasets/stair_ambulation_healthy_2021/scripts/create_pressure_events.py
gaitmap_datasets/utils/__init__.py
gaitmap_datasets/utils/array_handling.py
gaitmap_datasets/utils/c3d_loading.py
gaitmap_datasets/utils/consts.py
gaitmap_datasets/utils/coordinate_transforms.py
gaitmap_datasets/utils/data_loading.py
gaitmap_datasets/utils/egait_loading_helper.py
gaitmap_datasets/utils/event_detection.py
gaitmap_datasets-0.14.0.dist-info/LICENSE
gaitmap_datasets-0.14.0.dist-info/METADATA
gaitmap_datasets-0.14.0.dist-info/WHEEL
gaitmap_datasets-0.14.0.dist-info/RECORD
